new_alias/__init__.py
new_alias/main.py
new_alias/attributes/1-1000.txt
new_alias/attributes/first-names.txt
new_alias/attributes/last-names.txt
new_alias/attributes/pass_words.txt
new_alias/attributes/uname_words.txt
new_alias/attributes/words_alpha.txt
new_alias-1.0.2.dist-info/LICENSE
new_alias-1.0.2.dist-info/METADATA
new_alias-1.0.2.dist-info/WHEEL
new_alias-1.0.2.dist-info/entry_points.txt
new_alias-1.0.2.dist-info/top_level.txt
new_alias-1.0.2.dist-info/RECORD
