Metadata-Version: 2.1
Name: new-alias
Version: 1.0.2
Summary: An alias generator for online privacy protection
Home-page: https://github.com/Aiden2244/identity-generator
Author: Aiden R. McCormack
Author-email: aidenm2244@proton.me
License: UNKNOWN
Platform: UNKNOWN
Classifier: Programming Language :: Python :: 3
Classifier: License :: OSI Approved :: MIT License
Classifier: Operating System :: OS Independent
License-File: LICENSE
Requires-Dist: random-address (==1.1.1)
